cdk_remote_stack/__init__.py
cdk_remote_stack/py.typed
cdk_remote_stack/_jsii/__init__.py
cdk_remote_stack/_jsii/cdk-remote-stack@2.1.0.jsii.tgz
cdk_remote_stack-2.1.0.dist-info/LICENSE
cdk_remote_stack-2.1.0.dist-info/METADATA
cdk_remote_stack-2.1.0.dist-info/WHEEL
cdk_remote_stack-2.1.0.dist-info/top_level.txt
cdk_remote_stack-2.1.0.dist-info/RECORD
